pyscribus/__init__.py
pyscribus/file/__init__.py
pyscribus/file/colors.py
pyscribus/file/document.py
pyscribus/file/exceptions.py
pyscribus/file/hyphenation.py
pyscribus/file/pageobjects.py
pyscribus/file/stories.py
pyscribus/file/ui.py
pyscribus/model/__init__.py
pyscribus/model/colors.py
pyscribus/model/dimensions.py
pyscribus/model/document.py
pyscribus/model/exceptions.py
pyscribus/model/itemattribute.py
pyscribus/model/layers.py
pyscribus/model/logs.py
pyscribus/model/marks.py
pyscribus/model/notes.py
pyscribus/model/pageobjects.py
pyscribus/model/pages.py
pyscribus/model/patterns.py
pyscribus/model/printing.py
pyscribus/model/sla.py
pyscribus/model/stories.py
pyscribus/model/styles.py
pyscribus/model/toc.py
pyscribus/model/common/__init__.py
pyscribus/model/common/math.py
pyscribus/model/common/xml.py
pyscribus/model/extra/__init__.py
pyscribus/model/extra/wireframe.py
pyscribus/model/headless/__init__.py
pyscribus/model/headless/scripts/__init__.py
pyscribus/model/headless/scripts/topdf.py
pyscribus/model/papers/__init__.py
pyscribus/model/papers/afnor.py
pyscribus/model/papers/ansi.py
pyscribus/model/papers/iso216.py
pyscribus/model/papers/iso217.py
pyscribus/model/papers/iso269.py
pyscribus/model/papers/newspaper.py
pyscribus-0.3.dist-info/LICENSE
pyscribus-0.3.dist-info/METADATA
pyscribus-0.3.dist-info/WHEEL
pyscribus-0.3.dist-info/top_level.txt
pyscribus-0.3.dist-info/RECORD
